{
"meta":{"test_sets":[],"test_metrics":[],"learn_metrics":[{"best_value":"Min","name":"Logloss"}],"launch_mode":"Train","parameters":"","iteration_count":200,"learn_sets":["learn"],"name":"experiment"},
"iterations":[
{"learn":[0.6866112727],"iteration":0,"passed_time":0.006170760414,"remaining_time":1.227981322},
{"learn":[0.6820419785],"iteration":1,"passed_time":0.01172244015,"remaining_time":1.160521575},
{"learn":[0.677325346],"iteration":2,"passed_time":0.01715282935,"remaining_time":1.126369127},
{"learn":[0.6723309507],"iteration":3,"passed_time":0.02299792619,"remaining_time":1.126898383},
{"learn":[0.6667396779],"iteration":4,"passed_time":0.02848409227,"remaining_time":1.110879599},
{"learn":[0.6618784625],"iteration":5,"passed_time":0.03862075882,"remaining_time":1.248737869},
{"learn":[0.656981165],"iteration":6,"passed_time":0.04585573067,"remaining_time":1.264308003},
{"learn":[0.6521862196],"iteration":7,"passed_time":0.05340045677,"remaining_time":1.281610963},
{"learn":[0.6472566254],"iteration":8,"passed_time":0.0590464385,"remaining_time":1.253096639},
{"learn":[0.6431082469],"iteration":9,"passed_time":0.06380773605,"remaining_time":1.212346985},
{"learn":[0.6381592159],"iteration":10,"passed_time":0.06966470653,"remaining_time":1.196966321},
{"learn":[0.634201815],"iteration":11,"passed_time":0.07457874787,"remaining_time":1.168400383},
{"learn":[0.6300329213],"iteration":12,"passed_time":0.07951035098,"remaining_time":1.143725818},
{"learn":[0.6246713465],"iteration":13,"passed_time":0.08500017203,"remaining_time":1.129288},
{"learn":[0.6205106006],"iteration":14,"passed_time":0.08987952475,"remaining_time":1.108514139},
{"learn":[0.6163001147],"iteration":15,"passed_time":0.09466906493,"remaining_time":1.088694247},
{"learn":[0.6129572216],"iteration":16,"passed_time":0.09988879068,"remaining_time":1.075273453},
{"learn":[0.6095018952],"iteration":17,"passed_time":0.1047161877,"remaining_time":1.058797009},
{"learn":[0.605569978],"iteration":18,"passed_time":0.1096737798,"remaining_time":1.044787061},
{"learn":[0.6015489326],"iteration":19,"passed_time":0.1145282703,"remaining_time":1.030754432},
{"learn":[0.5972199635],"iteration":20,"passed_time":0.1193810753,"remaining_time":1.017581546},
{"learn":[0.5939090542],"iteration":21,"passed_time":0.1240717415,"remaining_time":1.003853181},
{"learn":[0.5897660495],"iteration":22,"passed_time":0.1287817822,"remaining_time":0.9910598025},
{"learn":[0.5862534072],"iteration":23,"passed_time":0.1335354174,"remaining_time":0.9792597279},
{"learn":[0.5826319382],"iteration":24,"passed_time":0.1385130465,"remaining_time":0.9695913257},
{"learn":[0.5794107316],"iteration":25,"passed_time":0.1432219145,"remaining_time":0.9584851204},
{"learn":[0.575658184],"iteration":26,"passed_time":0.1479215915,"remaining_time":0.947793901},
{"learn":[0.5724324356],"iteration":27,"passed_time":0.1527330851,"remaining_time":0.9382175225},
{"learn":[0.5686333704],"iteration":28,"passed_time":0.1574245009,"remaining_time":0.9282617122},
{"learn":[0.5643975926],"iteration":29,"passed_time":0.1622243318,"remaining_time":0.9192712136},
{"learn":[0.5605138279],"iteration":30,"passed_time":0.1682201664,"remaining_time":0.9170712297},
{"learn":[0.5571335247],"iteration":31,"passed_time":0.1730998668,"remaining_time":0.9087743007},
{"learn":[0.5539803227],"iteration":32,"passed_time":0.1778490715,"remaining_time":0.900024089},
{"learn":[0.5520984771],"iteration":33,"passed_time":0.1827009689,"remaining_time":0.8920106129},
{"learn":[0.5493691808],"iteration":34,"passed_time":0.1874154166,"remaining_time":0.8835298212},
{"learn":[0.5466615206],"iteration":35,"passed_time":0.192158668,"remaining_time":0.8753894874},
{"learn":[0.5435662402],"iteration":36,"passed_time":0.1969253837,"remaining_time":0.86753615},
{"learn":[0.5415889975],"iteration":37,"passed_time":0.201640119,"remaining_time":0.8596236653},
{"learn":[0.5391751721],"iteration":38,"passed_time":0.2064178516,"remaining_time":0.8521352334},
{"learn":[0.536259008],"iteration":39,"passed_time":0.2137702209,"remaining_time":0.8550808836},
{"learn":[0.5332828628],"iteration":40,"passed_time":0.2193679797,"remaining_time":0.850719726},
{"learn":[0.5307497324],"iteration":41,"passed_time":0.2254094619,"remaining_time":0.847968928},
{"learn":[0.5284077147],"iteration":42,"passed_time":0.230843849,"remaining_time":0.842848472},
{"learn":[0.5256460966],"iteration":43,"passed_time":0.2373316395,"remaining_time":0.8414485399},
{"learn":[0.5231074246],"iteration":44,"passed_time":0.2425426774,"remaining_time":0.8354247778},
{"learn":[0.5204977708],"iteration":45,"passed_time":0.2473948518,"remaining_time":0.8282349387},
{"learn":[0.5188575632],"iteration":46,"passed_time":0.2521893223,"remaining_time":0.8209567299},
{"learn":[0.5169747854],"iteration":47,"passed_time":0.2573123157,"remaining_time":0.8148223329},
{"learn":[0.5142554919],"iteration":48,"passed_time":0.2619601948,"remaining_time":0.8072650902},
{"learn":[0.5122731148],"iteration":49,"passed_time":0.2666110006,"remaining_time":0.7998330017},
{"learn":[0.5097616263],"iteration":50,"passed_time":0.271766053,"remaining_time":0.7939831745},
{"learn":[0.5075945491],"iteration":51,"passed_time":0.276316383,"remaining_time":0.7864389363},
{"learn":[0.5046675969],"iteration":52,"passed_time":0.28082196,"remaining_time":0.7788835495},
{"learn":[0.5032421551],"iteration":53,"passed_time":0.2854899256,"remaining_time":0.7718801692},
{"learn":[0.5011021987],"iteration":54,"passed_time":0.29036702,"remaining_time":0.7655130528},
{"learn":[0.4988288089],"iteration":55,"passed_time":0.2951945019,"remaining_time":0.7590715763},
{"learn":[0.4967613257],"iteration":56,"passed_time":0.3009544548,"remaining_time":0.7550260883},
{"learn":[0.4948998306],"iteration":57,"passed_time":0.3065403611,"remaining_time":0.7504953669},
{"learn":[0.4924827623],"iteration":58,"passed_time":0.3115337428,"remaining_time":0.7445128429},
{"learn":[0.4901068466],"iteration":59,"passed_time":0.3167697738,"remaining_time":0.7391294723},
{"learn":[0.4885957529],"iteration":60,"passed_time":0.3221147704,"remaining_time":0.7339992309},
{"learn":[0.4872374627],"iteration":61,"passed_time":0.3269177495,"remaining_time":0.7276556359},
{"learn":[0.4858418208],"iteration":62,"passed_time":0.3325473363,"remaining_time":0.7231584932},
{"learn":[0.4843957678],"iteration":63,"passed_time":0.3379596262,"remaining_time":0.7181642058},
{"learn":[0.4824834395],"iteration":64,"passed_time":0.3430169799,"remaining_time":0.7124198813},
{"learn":[0.4808255033],"iteration":65,"passed_time":0.3482165296,"remaining_time":0.7069850753},
{"learn":[0.4796679484],"iteration":66,"passed_time":0.354901567,"remaining_time":0.7045060957},
{"learn":[0.477685302],"iteration":67,"passed_time":0.3616055311,"remaining_time":0.7019401485},
{"learn":[0.4763446166],"iteration":68,"passed_time":0.4306800973,"remaining_time":0.8176680108},
{"learn":[0.4749586882],"iteration":69,"passed_time":0.455979121,"remaining_time":0.8468183675},
{"learn":[0.4734991345],"iteration":70,"passed_time":0.4801054427,"remaining_time":0.8723042551},
{"learn":[0.4716417353],"iteration":71,"passed_time":0.4908910968,"remaining_time":0.8726952832},
{"learn":[0.4701901241],"iteration":72,"passed_time":0.4963401451,"remaining_time":0.8634958689},
{"learn":[0.4685816714],"iteration":73,"passed_time":0.5192440003,"remaining_time":0.8841181627},
{"learn":[0.4669714937],"iteration":74,"passed_time":0.5383495983,"remaining_time":0.8972493305},
{"learn":[0.4655054091],"iteration":75,"passed_time":0.563861473,"remaining_time":0.9199845086},
{"learn":[0.4636690679],"iteration":76,"passed_time":0.5825711792,"remaining_time":0.9306007148},
{"learn":[0.4619943018],"iteration":77,"passed_time":0.5911967073,"remaining_time":0.9246922857},
{"learn":[0.4605819126],"iteration":78,"passed_time":0.5963953188,"remaining_time":0.9134662478},
{"learn":[0.458800562],"iteration":79,"passed_time":0.6017940874,"remaining_time":0.9026911311},
{"learn":[0.4575734791],"iteration":80,"passed_time":0.608156838,"remaining_time":0.8934649843},
{"learn":[0.4560412904],"iteration":81,"passed_time":0.6138996664,"remaining_time":0.8834165932},
{"learn":[0.4543586709],"iteration":82,"passed_time":0.6201038791,"remaining_time":0.8741223356},
{"learn":[0.4526832805],"iteration":83,"passed_time":0.6262548124,"remaining_time":0.8648280742},
{"learn":[0.4512435214],"iteration":84,"passed_time":0.6340488767,"remaining_time":0.8578308332},
{"learn":[0.4495744432],"iteration":85,"passed_time":0.6420595307,"remaining_time":0.8511021686},
{"learn":[0.44824267],"iteration":86,"passed_time":0.647736737,"remaining_time":0.8413132332},
{"learn":[0.4473266265],"iteration":87,"passed_time":0.653468663,"remaining_time":0.8316873893},
{"learn":[0.4459872311],"iteration":88,"passed_time":0.6590352974,"remaining_time":0.821942899},
{"learn":[0.4448315688],"iteration":89,"passed_time":0.6666269075,"remaining_time":0.8147662203},
{"learn":[0.4431627855],"iteration":90,"passed_time":0.6733748844,"remaining_time":0.8065699165},
{"learn":[0.441739239],"iteration":91,"passed_time":0.6793020996,"remaining_time":0.7974415952},
{"learn":[0.4402461637],"iteration":92,"passed_time":0.6856953193,"remaining_time":0.7889182706},
{"learn":[0.4387987136],"iteration":93,"passed_time":0.6915594984,"remaining_time":0.7798436897},
{"learn":[0.4376859347],"iteration":94,"passed_time":0.6975829332,"remaining_time":0.7710127157},
{"learn":[0.4367911779],"iteration":95,"passed_time":0.7042481176,"remaining_time":0.7629354607},
{"learn":[0.4353978154],"iteration":96,"passed_time":0.7096571851,"remaining_time":0.7535535058},
{"learn":[0.4343873161],"iteration":97,"passed_time":0.7154418153,"remaining_time":0.744643522},
{"learn":[0.4331914078],"iteration":98,"passed_time":0.7219331911,"remaining_time":0.7365177},
{"learn":[0.4321416728],"iteration":99,"passed_time":0.7280407127,"remaining_time":0.7280407127},
{"learn":[0.4310116882],"iteration":100,"passed_time":0.7341451509,"remaining_time":0.7196076231},
{"learn":[0.4301850612],"iteration":101,"passed_time":0.7401083312,"remaining_time":0.711084475},
{"learn":[0.4291350464],"iteration":102,"passed_time":0.7467682045,"remaining_time":0.7032671441},
{"learn":[0.4279292823],"iteration":103,"passed_time":0.7528981038,"remaining_time":0.694982865},
{"learn":[0.4265615363],"iteration":104,"passed_time":0.7590734703,"remaining_time":0.6867807589},
{"learn":[0.4255088837],"iteration":105,"passed_time":0.7654146412,"remaining_time":0.6787639271},
{"learn":[0.4245737175],"iteration":106,"passed_time":0.7718707297,"remaining_time":0.6708782978},
{"learn":[0.4237178679],"iteration":107,"passed_time":0.7784057495,"remaining_time":0.6630863792},
{"learn":[0.4227766259],"iteration":108,"passed_time":0.7845039598,"remaining_time":0.6549528472},
{"learn":[0.421850758],"iteration":109,"passed_time":0.7911388837,"remaining_time":0.6472954503},
{"learn":[0.4206120721],"iteration":110,"passed_time":0.797327682,"remaining_time":0.6392987721},
{"learn":[0.4198969109],"iteration":111,"passed_time":0.8034746904,"remaining_time":0.6313015425},
{"learn":[0.4185687874],"iteration":112,"passed_time":0.8109934947,"remaining_time":0.6243932216},
{"learn":[0.4174145312],"iteration":113,"passed_time":0.8175384198,"remaining_time":0.6167395097},
{"learn":[0.4164698994],"iteration":114,"passed_time":0.8237259806,"remaining_time":0.6088409422},
{"learn":[0.4157619801],"iteration":115,"passed_time":0.8320853418,"remaining_time":0.6025445578},
{"learn":[0.41482678],"iteration":116,"passed_time":0.8387404181,"remaining_time":0.5950038863},
{"learn":[0.414064182],"iteration":117,"passed_time":0.8445222006,"remaining_time":0.5868713598},
{"learn":[0.4130337632],"iteration":118,"passed_time":0.8517540031,"remaining_time":0.5797653298},
{"learn":[0.4119591347],"iteration":119,"passed_time":0.8602272966,"remaining_time":0.5734848644},
{"learn":[0.4114114497],"iteration":120,"passed_time":0.8657974244,"remaining_time":0.5652726986},
{"learn":[0.4105539157],"iteration":121,"passed_time":0.8728395174,"remaining_time":0.5580449373},
{"learn":[0.4096353234],"iteration":122,"passed_time":0.8800785402,"remaining_time":0.5509434764},
{"learn":[0.4090106165],"iteration":123,"passed_time":0.8905615025,"remaining_time":0.5458280176},
{"learn":[0.4080954846],"iteration":124,"passed_time":0.8967695693,"remaining_time":0.5380617416},
{"learn":[0.4074144976],"iteration":125,"passed_time":0.9034384003,"remaining_time":0.5305908065},
{"learn":[0.4065014832],"iteration":126,"passed_time":0.9257794892,"remaining_time":0.5321409662},
{"learn":[0.4059425794],"iteration":127,"passed_time":0.9318682421,"remaining_time":0.5241758862},
{"learn":[0.4051630696],"iteration":128,"passed_time":0.9392980611,"remaining_time":0.5169780026},
{"learn":[0.4043811723],"iteration":129,"passed_time":0.9490171418,"remaining_time":0.5110092302},
{"learn":[0.403778147],"iteration":130,"passed_time":0.9700961252,"remaining_time":0.5109666614},
{"learn":[0.40257605],"iteration":131,"passed_time":0.9978984602,"remaining_time":0.5140689037},
{"learn":[0.401585923],"iteration":132,"passed_time":1.040298446,"remaining_time":0.5240601193},
{"learn":[0.4005568758],"iteration":133,"passed_time":1.046994138,"remaining_time":0.51568368},
{"learn":[0.3999188428],"iteration":134,"passed_time":1.053900881,"remaining_time":0.5074337573},
{"learn":[0.3989877498],"iteration":135,"passed_time":1.059783769,"remaining_time":0.4987217738},
{"learn":[0.3984148349],"iteration":136,"passed_time":1.065205069,"remaining_time":0.4898388273},
{"learn":[0.3976698514],"iteration":137,"passed_time":1.071368735,"remaining_time":0.4813395766},
{"learn":[0.3969187425],"iteration":138,"passed_time":1.077734224,"remaining_time":0.472962501},
{"learn":[0.3959392701],"iteration":139,"passed_time":1.08561852,"remaining_time":0.4652650801},
{"learn":[0.3951138694],"iteration":140,"passed_time":1.091475151,"remaining_time":0.4567165526},
{"learn":[0.394066876],"iteration":141,"passed_time":1.09950821,"remaining_time":0.4490949027},
{"learn":[0.3936423214],"iteration":142,"passed_time":1.105973932,"remaining_time":0.4408427559},
{"learn":[0.3929887597],"iteration":143,"passed_time":1.111820108,"remaining_time":0.4323744864},
{"learn":[0.392481215],"iteration":144,"passed_time":1.118274044,"remaining_time":0.4241729134},
{"learn":[0.3919268491],"iteration":145,"passed_time":1.124197726,"remaining_time":0.4157991589},
{"learn":[0.3916363349],"iteration":146,"passed_time":1.132401218,"remaining_time":0.4082807111},
{"learn":[0.390809907],"iteration":147,"passed_time":1.13945559,"remaining_time":0.4003492612},
{"learn":[0.3900963789],"iteration":148,"passed_time":1.146561424,"remaining_time":0.3924471987},
{"learn":[0.3888670724],"iteration":149,"passed_time":1.151950002,"remaining_time":0.3839833339},
{"learn":[0.3876822937],"iteration":150,"passed_time":1.157467158,"remaining_time":0.3756019253},
{"learn":[0.3871512734],"iteration":151,"passed_time":1.163383701,"remaining_time":0.3673843268},
{"learn":[0.386269097],"iteration":152,"passed_time":1.168977957,"remaining_time":0.3590978039},
{"learn":[0.3856152575],"iteration":153,"passed_time":1.175434138,"remaining_time":0.3511037035},
{"learn":[0.3847403445],"iteration":154,"passed_time":1.181593729,"remaining_time":0.3430433408},
{"learn":[0.3840727879],"iteration":155,"passed_time":1.192647157,"remaining_time":0.3363876596},
{"learn":[0.3830988976],"iteration":156,"passed_time":1.198788133,"remaining_time":0.3283305077},
{"learn":[0.3827085258],"iteration":157,"passed_time":1.204742931,"remaining_time":0.3202481208},
{"learn":[0.3817668725],"iteration":158,"passed_time":1.211049155,"remaining_time":0.3122831154},
{"learn":[0.3811829477],"iteration":159,"passed_time":1.216900541,"remaining_time":0.3042251352},
{"learn":[0.3806498326],"iteration":160,"passed_time":1.223213731,"remaining_time":0.2963064317},
{"learn":[0.3799281873],"iteration":161,"passed_time":1.229364539,"remaining_time":0.2883694598},
{"learn":[0.3791868436],"iteration":162,"passed_time":1.235240634,"remaining_time":0.2803920458},
{"learn":[0.3784070144],"iteration":163,"passed_time":1.243473796,"remaining_time":0.2729576625},
{"learn":[0.3776242657],"iteration":164,"passed_time":1.248862808,"remaining_time":0.2649102925},
{"learn":[0.3770563957],"iteration":165,"passed_time":1.255043987,"remaining_time":0.2570572022},
{"learn":[0.3765251933],"iteration":166,"passed_time":1.260348165,"remaining_time":0.249050835},
{"learn":[0.3760049102],"iteration":167,"passed_time":1.26627941,"remaining_time":0.2411960781},
{"learn":[0.3756439047],"iteration":168,"passed_time":1.275163761,"remaining_time":0.2339057786},
{"learn":[0.374941432],"iteration":169,"passed_time":1.280686497,"remaining_time":0.2260034994},
{"learn":[0.3744197575],"iteration":170,"passed_time":1.288161404,"remaining_time":0.2184601211},
{"learn":[0.3735604839],"iteration":171,"passed_time":1.293849798,"remaining_time":0.2106267113},
{"learn":[0.3728885847],"iteration":172,"passed_time":1.30188278,"remaining_time":0.2031840177},
{"learn":[0.3725354574],"iteration":173,"passed_time":1.308027035,"remaining_time":0.1954523156},
{"learn":[0.3721293072],"iteration":174,"passed_time":1.314743073,"remaining_time":0.187820439},
{"learn":[0.3716135485],"iteration":175,"passed_time":1.321063995,"remaining_time":0.1801450902},
{"learn":[0.3711329361],"iteration":176,"passed_time":1.326845011,"remaining_time":0.1724148885},
{"learn":[0.3703869839],"iteration":177,"passed_time":1.332919693,"remaining_time":0.1647428835},
{"learn":[0.3699047519],"iteration":178,"passed_time":1.337944203,"remaining_time":0.156965521},
{"learn":[0.3692512467],"iteration":179,"passed_time":1.345030637,"remaining_time":0.1494478485},
{"learn":[0.3687229996],"iteration":180,"passed_time":1.351018448,"remaining_time":0.1418196161},
{"learn":[0.3680713397],"iteration":181,"passed_time":1.356924493,"remaining_time":0.1342013234},
{"learn":[0.3676992677],"iteration":182,"passed_time":1.362686497,"remaining_time":0.1265883631},
{"learn":[0.3671100932],"iteration":183,"passed_time":1.37053473,"remaining_time":0.119176933},
{"learn":[0.3661634646],"iteration":184,"passed_time":1.376739423,"remaining_time":0.1116275208},
{"learn":[0.3655107222],"iteration":185,"passed_time":1.386635455,"remaining_time":0.1043704106},
{"learn":[0.3647026244],"iteration":186,"passed_time":1.393411325,"remaining_time":0.09686816701},
{"learn":[0.3640999729],"iteration":187,"passed_time":1.399453475,"remaining_time":0.08932681754},
{"learn":[0.3636312897],"iteration":188,"passed_time":1.405519515,"remaining_time":0.0818027231},
{"learn":[0.3632177072],"iteration":189,"passed_time":1.41136126,"remaining_time":0.07428217157},
{"learn":[0.3626260114],"iteration":190,"passed_time":1.417138575,"remaining_time":0.06677616324},
{"learn":[0.3619924057],"iteration":191,"passed_time":1.423357092,"remaining_time":0.0593065455},
{"learn":[0.3612832898],"iteration":192,"passed_time":1.429266191,"remaining_time":0.05183867016},
{"learn":[0.3608850674],"iteration":193,"passed_time":1.436457449,"remaining_time":0.04442651903},
{"learn":[0.3603045167],"iteration":194,"passed_time":1.445109251,"remaining_time":0.03705408336},
{"learn":[0.3599011803],"iteration":195,"passed_time":1.452742177,"remaining_time":0.02964779954},
{"learn":[0.3594753549],"iteration":196,"passed_time":1.460464306,"remaining_time":0.02224057318},
{"learn":[0.3586095362],"iteration":197,"passed_time":1.466415735,"remaining_time":0.01481228015},
{"learn":[0.3581177124],"iteration":198,"passed_time":1.471639947,"remaining_time":0.007395175611},
{"learn":[0.3577678005],"iteration":199,"passed_time":1.477893758,"remaining_time":0}
]}